dumbo_runlim/__init__.py
dumbo_runlim/__main__.py
dumbo_runlim/cli.py
dumbo_runlim/experiments/__init__.py
dumbo_runlim/experiments/example.py
dumbo_runlim/experiments/ucorexplain.py
dumbo_runlim/experiments/xasp.py
dumbo_runlim/utils.py
dumbo_runlim-0.2.7.dist-info/LICENSE
dumbo_runlim-0.2.7.dist-info/METADATA
dumbo_runlim-0.2.7.dist-info/WHEEL
dumbo_runlim-0.2.7.dist-info/RECORD
