Metadata-Version: 2.1
Name: dumbo-runlim
Version: 0.2.7
Summary: A CLI to run and limit processes (and their subprocesses)
Author: Mario Alviano
Author-email: mario.alviano@gmail.com
Requires-Python: >=3.11,<4.0
Classifier: Programming Language :: Python :: 3
Classifier: Programming Language :: Python :: 3.11
Classifier: Programming Language :: Python :: 3.12
Requires-Dist: dumbo-utils (>=0.3.2,<0.4.0)
Requires-Dist: gitpython (>=3.1.42,<4.0.0)
Requires-Dist: psutil (>=5.9.7,<6.0.0)
